.mica_settings
.project
.pydevproject
LICENCE
MANIFEST.in
ez_setup.py
setup.cfg
setup.py
.settings/org.eclipse.core.resources.prefs
hildon/mougeon.desktop
hildon/icons/48x48/mougeon.png
hildon/icons/64x64/mougeon.png
media/mougeon.png
media/mouton.mp3
media/pigeon.wav
scripts/mougeon
scripts/mougeon-status.sh
src/mougeon/Broken-chains.gif
src/mougeon/__init__.py
src/mougeon/bootstrap.py
src/mougeon/mougeon-logo.png
src/mougeon/mouton.wav
src/mougeon/orange.jpg
src/mougeon/pigeon.wav
src/mougeon.egg-info/PKG-INFO
src/mougeon.egg-info/SOURCES.txt
src/mougeon.egg-info/dependency_links.txt
src/mougeon.egg-info/not-zip-safe
src/mougeon.egg-info/requires.txt
src/mougeon.egg-info/top_level.txt
src/mougeon/common/__init__.py
src/mougeon/common/version.py
src/mougeon/core/__init__.py
src/mougeon/core/exceptions.py
src/mougeon/core/facade.py
src/mougeon/core/model.py
src/mougeon/core/utils.py
src/mougeon/core/persistence/__init__.py
src/mougeon/core/persistence/dao.py
src/mougeon/gui/__init__.py
src/mougeon/gui/gtk/__init__.py
src/mougeon/gui/gtk/utils.py
src/mougeon/gui/gtk/widget.py
src/mougeon/gui/hildon/__init__.py
src/mougeon/gui/hildon/mougeonGui.py
src/mougeon/gui/hildon/portrait.py
src/mougeon/gui/hildon/utils.py
src/mougeon/gui/hildon/widget.py