Metadata-Version: 1.0
Name: mougeon
Version: 0.1.0dev-r48
Summary: Free Mobile Cell Tower usage tracker
Home-page: http://blog.mougeon.bressure.net
Author: Thierry Bressure
Author-email: mougeon@bressure.net
License: UNKNOWN
Download-URL: http://mougeon.bressure.net
Platform: UNKNOWN
Classifier: Development Status :: 2 - Pre-Alpha
Classifier: Environment :: Handhelds/PDA's
Classifier: Intended Audience :: End Users/Desktop
Classifier: Intended Audience :: Developers
Classifier: License :: OSI Approved :: GNU Library or Lesser General Public License (LGPL)
Classifier: Operating System :: POSIX :: Linux
Classifier: Programming Language :: Python
